besuto/__init__.py
besuto/images/__init__.py
besuto/images/augment.py
besuto/images/vggFace.py
besuto-0.0.5.dist-info/METADATA
besuto-0.0.5.dist-info/WHEEL
besuto-0.0.5.dist-info/top_level.txt
besuto-0.0.5.dist-info/RECORD
